README.rst
setup.py
pyprofiler/__init__.py
pyprofiler.egg-info/PKG-INFO
pyprofiler.egg-info/SOURCES.txt
pyprofiler.egg-info/dependency_links.txt
pyprofiler.egg-info/top_level.txt
pyprofiler.egg-info/zip-safe